gqvis/__init__.py
gqvis/gqvis.py
gqvis/template/dummyData.js
gqvis/template/graphVisualisation.js
gqvis/template/template.html
gqvis-0.1.15.dist-info/License.md
gqvis-0.1.15.dist-info/WHEEL
gqvis-0.1.15.dist-info/METADATA
gqvis-0.1.15.dist-info/RECORD
